naganlp/__init__.py
naganlp/nltk_tagger.py
naganlp/nmt_translator.py
naganlp/nmt_translator.txt
naganlp/subword_tokenizer.py
naganlp/transformer_tagger.py
naganlp/word_aligner.py
naganlp/data/__init__.py
naganlp/data/nagamese_english_spm.model
naganlp/data/nagamese_nltk_tagger.pkl
naganlp-0.1.1.dist-info/licenses/LICENSE
naganlp-0.1.1.dist-info/METADATA
naganlp-0.1.1.dist-info/WHEEL
naganlp-0.1.1.dist-info/top_level.txt
naganlp-0.1.1.dist-info/RECORD
