Metadata-Version: 2.4
Name: naganlp
Version: 0.1.1
Summary: A Natural Language Processing toolkit for the Nagamese language.
Home-page: https://github.com/AgnivaMaiti/naga-nlp
Author: Agniva Maiti
Author-email: Agniva Maiti <agnivamaiti.official@gmail.com>
License: MIT License
Project-URL: Homepage, https://github.com/AgnivaMaiti/naga-nlp
Project-URL: Bug Tracker, https://github.com/AgnivaMaiti/naga-nlp/issues
Project-URL: Repository, https://github.com/AgnivaMaiti/naga-nlp
Project-URL: Documentation, https://github.com/AgnivaMaiti/naga-nlp#readme
Keywords: nlp,nagamese,natural-language-processing,machine-translation,pos-tagging
Classifier: Development Status :: 3 - Alpha
Classifier: Intended Audience :: Science/Research
Classifier: Intended Audience :: Developers
Classifier: License :: OSI Approved :: MIT License
Classifier: Natural Language :: English
Classifier: Programming Language :: Python :: 3
Classifier: Programming Language :: Python :: 3.8
Classifier: Programming Language :: Python :: 3.9
Classifier: Programming Language :: Python :: 3.10
Classifier: Programming Language :: Python :: 3.11
Classifier: Topic :: Scientific/Engineering
Classifier: Topic :: Scientific/Engineering :: Artificial Intelligence
Classifier: Topic :: Text Processing
Classifier: Topic :: Text Processing :: Linguistic
Requires-Python: >=3.8
License-File: LICENSE
Requires-Dist: numpy<2.0.0
Requires-Dist: nltk>=3.8.1
Requires-Dist: sentencepiece>=0.1.99
Requires-Dist: transformers<5.0.0,>=4.30.0
Requires-Dist: torch<2.9.0,>=2.0.0
Requires-Dist: datasets<3.0.0,>=2.0.0
Requires-Dist: scikit-learn<2.0.0,>=1.0.0
Requires-Dist: pandas<3.0.0,>=1.3.0
Requires-Dist: importlib-resources>=5.12.0; python_version < "3.9"
Provides-Extra: dev
Requires-Dist: pytest>=7.0.0; extra == "dev"
Requires-Dist: black>=23.0.0; extra == "dev"
Requires-Dist: isort>=5.0.0; extra == "dev"
Requires-Dist: mypy>=1.0.0; extra == "dev"
Requires-Dist: flake8>=6.0.0; extra == "dev"
Dynamic: author
Dynamic: home-page
Dynamic: license-file
Dynamic: requires-python
